clion.py
clion-0.3.2.dist-info/WHEEL
clion-0.3.2.dist-info/METADATA
clion-0.3.2.dist-info/RECORD
